{"code":200,"status":"SUCCESS","home":{"banner":"http://mlife02.wasys.com.br:8080/c2shmg/resources/design/images/background-banner.jpg","titulos":["Conheça o chef e reserve um lugar","Compartilhe Experiências"],"eventos":[{"id":"19","titulo":"Incríveis sabores da Italia","imagem":{"id":"195","url":"http://res.cloudinary.com/dqmytkp5f/image/upload/195.jpg","cloudinary":{"name":"dqmytkp5f","apiKey":"226796523957175","apiSecret":"w2xyjER5zyoBkjlRjwg1EmadvLM"}},"chef":{"nome":"Caroline Godoy","avaliacaoMedia":4.933333333333334,"imagem":{"id":"53","url":"http://res.cloudinary.com/dqmytkp5f/image/upload/53.jpg","cloudinary":{"name":"dqmytkp5f","apiKey":"226796523957175","apiSecret":"w2xyjER5zyoBkjlRjwg1EmadvLM"}}}},{"id":"14","titulo":"Pão no Bafo","imagem":{"id":"161","url":"http://res.cloudinary.com/dqmytkp5f/image/upload/161.jpg","cloudinary":{"name":"dqmytkp5f","apiKey":"226796523957175","apiSecret":"w2xyjER5zyoBkjlRjwg1EmadvLM"}},"chef":{"nome":"Rosane Radecki de Oliveira","avaliacaoMedia":0,"imagem":{"id":"54","url":"http://res.cloudinary.com/dqmytkp5f/image/upload/54.jpg","cloudinary":{"name":"dqmytkp5f","apiKey":"226796523957175","apiSecret":"w2xyjER5zyoBkjlRjwg1EmadvLM"}}}},{"id":"32","titulo":"Confraria O Vinho é Delas","imagem":{"id":"209","url":"http://res.cloudinary.com/dqmytkp5f/image/upload/209.jpg","cloudinary":{"name":"dqmytkp5f","apiKey":"226796523957175","apiSecret":"w2xyjER5zyoBkjlRjwg1EmadvLM"}},"chef":{"nome":"Claudinei Oliveira ","avaliacaoMedia":4.6,"imagem":{"id":"57","url":"http://res.cloudinary.com/dqmytkp5f/image/upload/57.jpg","cloudinary":{"name":"dqmytkp5f","apiKey":"226796523957175","apiSecret":"w2xyjER5zyoBkjlRjwg1EmadvLM"}}}},{"id":"22","titulo":"Olé, Paella!","imagem":{"id":"190","url":"http://res.cloudinary.com/dqmytkp5f/image/upload/190.jpg","cloudinary":{"name":"dqmytkp5f","apiKey":"226796523957175","apiSecret":"w2xyjER5zyoBkjlRjwg1EmadvLM"}},"chef":{"nome":"Alexandre Bressanelli","avaliacaoMedia":0,"imagem":{"id":"60","url":"http://res.cloudinary.com/dqmytkp5f/image/upload/60.jpg","cloudinary":{"name":"dqmytkp5f","apiKey":"226796523957175","apiSecret":"w2xyjER5zyoBkjlRjwg1EmadvLM"}}}},{"id":"44","titulo":"Delicioso Jantar com harmonização ","imagem":{"id":"242","url":"http://res.cloudinary.com/dqmytkp5f/image/upload/242.jpg","cloudinary":{"name":"dqmytkp5f","apiKey":"226796523957175","apiSecret":"w2xyjER5zyoBkjlRjwg1EmadvLM"}},"chef":{"nome":"Luis Henrique","avaliacaoMedia":0,"imagem":{"id":"62","url":"http://res.cloudinary.com/dqmytkp5f/image/upload/62.jpg","cloudinary":{"name":"dqmytkp5f","apiKey":"226796523957175","apiSecret":"w2xyjER5zyoBkjlRjwg1EmadvLM"}}}},{"id":"24","titulo":"Workshop Receitas Fit","imagem":{"id":"200","url":"http://res.cloudinary.com/dqmytkp5f/image/upload/200.jpg","cloudinary":{"name":"dqmytkp5f","apiKey":"226796523957175","apiSecret":"w2xyjER5zyoBkjlRjwg1EmadvLM"}},"chef":{"nome":"Claudia de Figueiredo","avaliacaoMedia":0,"imagem":{"id":"63","url":"http://res.cloudinary.com/dqmytkp5f/image/upload/63.jpg","cloudinary":{"name":"dqmytkp5f","apiKey":"226796523957175","apiSecret":"w2xyjER5zyoBkjlRjwg1EmadvLM"}}}}]}}